[{
		"avatar": "https://cdn.jsdelivr.net/gh/athink8/athink8.github.io/medias/logo.png",
		"name": "Athink_工具箱",
		"introduction": "折折腾腾,梦想实现",
		"url": "https://tool.onfree.cn/",
		"title": "前去瞧瞧"
	},{
		"avatar": "https://cdn.jsdelivr.net/gh/athink8/athink8.github.io/medias/logo.png",
		"name": "Athink_影视",
		"introduction": "陪伴你欢乐时光",
		"url": "https://movie.onfree.cn/",
		"title": "前去瞧瞧"
	},{
		"avatar": "https://uixsj.cn/favicon.ico",
		"name": "现实君",
		"introduction": "回归现实，分享有趣<br>",
		"url": "https://uixsj.cn/",
		"title": "前去学习"
	},
	{
		"avatar": "https://cdn.jsdelivr.net/gh/Aunger-ops/myblog@latest/images/touch-icon.png",
		"name": "Aunger’s Blog",
		"introduction": "Aunger’s Blog | 热爱的事物要不遗余力。",
		"url": "https://www.webaun.cn/",
		"title": "前去学习"
	},
	{
		"avatar": "http://suo.im/5tTMXe",
		"name": "zzzain46’s Blog",
		"introduction": "能全力以赴不尽力而为",
		"url": "https://www.52debug.cn",
		"title": "前去学习"
	},
	{
		"avatar": "https://xiaochamao.com/tx.png",
		"name": "小茶猫",
		"introduction": "主要发布一些日常或者转载的东西吧，还有就是一些学习的经历。",
		"url": "https://xiaochamao.com",
		"title": "前去学习"
	},
	{
		"avatar": "https://www.qxwlmz.cn/logo.png",
		"name": "倾心博客",
		"introduction": "爱网络、重情义、乐生活",
		"url": "https://www.qxwlmz.cn",
		"title": "前去学习"
	},
	{
		"avatar": "https://a-oss.zmki.cn/20190601/img_9878.jpg",
		"name": "钻芒博客",
		"introduction": "崇尚技术，乐享极致",
		"url": "https://www.zmki.cn",
		"title": "前去学习"
	},
	{
		"avatar": "https://www.zylearning.top/blogfavicon.ico",
		"name": "最要学习",
		"introduction": "最要学习|记录点滴",
		"url": "https://www.zylearning.top/",
		"title": "前去学习"
	}
]
